README.txt
setup.py
django_template_coverage.egg-info/PKG-INFO
django_template_coverage.egg-info/SOURCES.txt
django_template_coverage.egg-info/dependency_links.txt
django_template_coverage.egg-info/entry_points.txt
django_template_coverage.egg-info/not-zip-safe
django_template_coverage.egg-info/requires.txt
django_template_coverage.egg-info/top_level.txt
dtcov/__init__.py
dtcov/__main__.py
dtcov/dt_coverage.py
dtcov/dt_django.py
dtcov/dt_file_utils.py
dtcov/dt_help.py
dtcov/dt_log.py
dtcov/dt_report.py
dtcov/dt_tracer.py
dtcov/run_coverage.py
test/test_parser.py