Metadata-Version: 1.1
Name: django-template-coverage
Version: 0.1.0
Summary: Coverage tool for Django templates
Home-page: url to coverage
Author: Dmitry Trofimov
Author-email: dmitry.trofimov@jetbrains.com
License: BSD
Keywords: django code coverage testing
Platform: UNKNOWN
Classifier: Environment :: Console
Classifier: Intended Audience :: Developers
Classifier: License :: OSI Approved :: BSD License
Classifier: Operating System :: OS Independent
Classifier: Programming Language :: Python :: 2
Classifier: Topic :: Software Development :: Quality Assurance
Classifier: Topic :: Software Development :: Testing
Classifier: Development Status :: 5 - Production/Stable
